SnakeTeX-0.1.3.dist-info/DESCRIPTION.rst
SnakeTeX-0.1.3.dist-info/METADATA
SnakeTeX-0.1.3.dist-info/RECORD
SnakeTeX-0.1.3.dist-info/WHEEL
SnakeTeX-0.1.3.dist-info/entry_points.txt
SnakeTeX-0.1.3.dist-info/metadata.json
SnakeTeX-0.1.3.dist-info/top_level.txt
site/__init__.py
