Metadata-Version: 2.0
Name: SnakeTeX
Version: 0.1.3
Summary: A LaTeX template system for large and multi-user projects.
Home-page: https://github.com/opieters/SnakeTeX
Author: Olivier Pieters
Author-email: me@olivierpieters.be
License: GPLv3
Keywords: LaTeX TeX XeTeX documents template system
Platform: UNKNOWN
Classifier: Development Status :: 3 - Alpha
Classifier: Topic :: Text Processing :: Markup :: LaTeX
Classifier: License :: OSI Approved :: GNU General Public License v3 (GPLv3)
Classifier: Programming Language :: Python :: 3.5
Requires-Dist: Jinja2
Requires-Dist: PyYAML
Requires-Dist: click
